py_travel/__init__.py
py_travel/client.py
py_travel/exceptions.py
py_travel/location.py
py_travel/utils.py
py_travel/vars.py
py_travel/trip/__init__.py
py_travel/trip/stop.py
py_travel/trip/trip.py
py_travel/trip/trip_config.py
py_travel-0.1.1.dist-info/METADATA
py_travel-0.1.1.dist-info/WHEEL
py_travel-0.1.1.dist-info/licenses/LICENSE
py_travel-0.1.1.dist-info/RECORD
