Metadata-Version: 2.3
Name: py_travel
Version: 0.1.1
Summary: Plan trips using the Google Maps API
Project-URL: Homepage, https://github.com/diagmatrix/py_travel
Project-URL: Issues, https://github.com/diagmatrix/py_travel/issues
Author-email: diagmatrix <manuel.gachs@gmail.com>
License-File: LICENSE
Classifier: Development Status :: 3 - Alpha
Classifier: License :: OSI Approved :: GNU General Public License v3 (GPLv3)
Classifier: Operating System :: OS Independent
Classifier: Programming Language :: Python :: 3
Requires-Python: >=3.10
Requires-Dist: googlemaps>=4.10.0
